{
  "credit": "Made by Skart2000",
  "parent": "minecraft:block/block",
  "render_type": "minecraft:cutout",
  "texture_size": [64, 64],
  "textures": {
    "particle": "tanukidecor:block/regal_vanity",
    "vanity": "tanukidecor:block/regal_vanity"
  },
  "elements": [
    {
      "name": "leg_0",
      "from": [0, 0, 0],
      "to": [2, 8, 2],
      "faces": {
        "north": {"uv": [4, 0, 4.5, 2], "texture": "#vanity"},
        "east": {"uv": [4.5, 0, 4, 2], "texture": "#vanity"},
        "south": {"uv": [4, 0, 4.5, 2], "texture": "#vanity"},
        "west": {"uv": [4.5, 0, 4, 2], "texture": "#vanity"},
        "down": {"uv": [4, 2, 4.5, 2.5], "texture": "#vanity"}
      }
    },
    {
      "name": "leg_1",
      "from": [14, 0, 0],
      "to": [16, 8, 2],
      "faces": {
        "north": {"uv": [4.5, 0, 4, 2], "texture": "#vanity"},
        "east": {"uv": [4, 0, 4.5, 2], "texture": "#vanity"},
        "south": {"uv": [4.5, 0, 4, 2], "texture": "#vanity"},
        "west": {"uv": [4, 0, 4.5, 2], "texture": "#vanity"},
        "down": {"uv": [4.5, 2, 4, 2.5], "texture": "#vanity"}
      }
    },
    {
      "name": "leg_2",
      "from": [0, 0, 14],
      "to": [2, 8, 16],
      "faces": {
        "north": {"uv": [4.5, 0, 4, 2], "texture": "#vanity"},
        "east": {"uv": [4, 0, 4.5, 2], "texture": "#vanity"},
        "south": {"uv": [4.5, 0, 4, 2], "texture": "#vanity"},
        "west": {"uv": [4, 0, 4.5, 2], "texture": "#vanity"},
        "down": {"uv": [4, 2.5, 4.5, 2], "texture": "#vanity"}
      }
    },
    {
      "name": "leg_3",
      "from": [14, 0, 14],
      "to": [16, 8, 16],
      "faces": {
        "north": {"uv": [4, 0, 4.5, 2], "texture": "#vanity"},
        "east": {"uv": [4.5, 0, 4, 2], "texture": "#vanity"},
        "south": {"uv": [4, 0, 4.5, 2], "texture": "#vanity"},
        "west": {"uv": [4.5, 0, 4, 2], "texture": "#vanity"},
        "down": {"uv": [4.5, 2.5, 4, 2], "texture": "#vanity"}
      }
    },
    {
      "name": "table_0",
      "from": [0, 8, 0],
      "to": [16, 16, 16],
      "faces": {
        "north": {"uv": [0, 0, 4, 2], "texture": "#vanity"},
        "east": {"uv": [0, 2, 4, 4], "texture": "#vanity"},
        "south": {"uv": [0, 4, 4, 6], "texture": "#vanity"},
        "west": {"uv": [0, 2, 4, 4], "texture": "#vanity"},
        "up": {"uv": [0, 6, 4, 10], "texture": "#vanity"},
        "down": {"uv": [0, 6, 4, 10], "texture": "#vanity"}
      }
    },
    {
      "name": "table_1",
      "from": [2, 6, 0],
      "to": [14, 8, 0],
      "faces": {
        "north": {"uv": [0, 10, 3, 10.5], "texture": "#vanity"},
        "east": {"uv": [0, 10, 0, 10.5], "texture": "#vanity"},
        "south": {"uv": [3, 10, 0, 10.5], "texture": "#vanity"},
        "west": {"uv": [0, 10, 0, 10.5], "texture": "#vanity"},
        "up": {"uv": [0, 10, 3, 10], "texture": "#vanity"},
        "down": {"uv": [0, 10, 3, 10], "texture": "#vanity"}
      }
    },
    {
      "name": "table_2",
      "from": [2, 6, 16],
      "to": [14, 8, 16],
      "faces": {
        "north": {"uv": [0, 10, 3, 10.5], "texture": "#vanity"},
        "east": {"uv": [0, 10, 0, 10.5], "texture": "#vanity"},
        "south": {"uv": [3, 10, 0, 10.5], "texture": "#vanity"},
        "west": {"uv": [0, 10, 0, 10.5], "texture": "#vanity"},
        "up": {"uv": [0, 10, 3, 10], "texture": "#vanity"},
        "down": {"uv": [0, 10, 3, 10], "texture": "#vanity"}
      }
    },
    {
      "name": "table_3",
      "from": [0, 6, 2],
      "to": [0, 8, 14],
      "faces": {
        "north": {"uv": [0, 10, 0, 10.5], "texture": "#vanity"},
        "east": {"uv": [0, 10, 3, 10.5], "texture": "#vanity"},
        "south": {"uv": [0, 10, 0, 10.5], "texture": "#vanity"},
        "west": {"uv": [0, 10, 3, 10.5], "texture": "#vanity"},
        "up": {"uv": [0, 10, 0, 13], "texture": "#vanity"},
        "down": {"uv": [0, 10, 0, 13], "texture": "#vanity"}
      }
    },
    {
      "name": "table_4",
      "from": [16, 6, 2],
      "to": [16, 8, 14],
      "faces": {
        "north": {"uv": [0, 10, 0, 10.5], "texture": "#vanity"},
        "east": {"uv": [0, 10, 3, 10.5], "texture": "#vanity"},
        "south": {"uv": [0, 10, 0, 10.5], "texture": "#vanity"},
        "west": {"uv": [0, 10, 3, 10.5], "texture": "#vanity"},
        "up": {"uv": [0, 10, 0, 13], "texture": "#vanity"},
        "down": {"uv": [0, 10, 0, 13], "texture": "#vanity"}
      }
    }
  ],
  "groups": [
    {
      "name": "bottom",
      "origin": [8, 8, 8],
      "color": 0,
      "children": [0, 1, 2, 3, 4, 5, 6, 7, 8]
    }
  ]
}